cvsvc_apirisk/__init__.py
cvsvc_apirisk/cvapirisk_pkg/API_Risk_Assessment_OB.pdf
cvsvc_apirisk/cvapirisk_pkg/CloudVector-APIRiskTool-Documentation.pdf
cvsvc_apirisk/cvapirisk_pkg/cv_rules_sample.json
cvsvc_apirisk/cvapirisk_pkg/example_cmds.txt
cvsvc_apirisk/cvapirisk_pkg/orangebank.zip
cvsvc_apirisk/cvapirisk_pkg/orangebank_user.json
cvsvc_apirisk/cvapirisk_pkg/orangebank_user_orig.json
cvsvc_apirisk/score/__init__.py
cvsvc_apirisk/score/base.py
cvsvc_apirisk/score/spec_security/__init__.py
cvsvc_apirisk/score/spec_security/apisparc_server.cfg
cvsvc_apirisk/score/spec_security/cv_apirisk_assessment.py
cvsvc_apirisk/score/spec_security/cv_apirisk_server.py
cvsvc_apirisk/score/spec_security/json_line.py
cvsvc_apirisk/score/spec_security/rules_util.py
cvsvc_apirisk/score/spec_security/s-origin.py
cvsvc_apirisk/score/spec_security/sp2_reporting.py
cvsvc_apirisk/score/spec_security/sparc_html_generation.py
cvsvc_apirisk/score/spec_security/spec_parse.py
cvsvc_apirisk/score/spec_security/spec_util.py
cvsvc_apirisk/score/spec_security/sps_common.py
cvsvc_apirisk/score/spec_security/sps_main.py
cvsvc_apirisk/score/spec_security/sps_main_cr.py
cvsvc_apirisk/score/spec_security/sps_spec_util.py
cvsvc_apirisk/score/spec_security/yaml_line.py
cvsvc_apirisk/score/spec_security/data_attrs/__init__.py
cvsvc_apirisk/score/spec_security/data_attrs/sps_data_attr01.py
cvsvc_apirisk/score/spec_security/data_attrs/sps_data_attr02.py
cvsvc_apirisk/score/spec_security/data_attrs/sps_data_attr03.py
cvsvc_apirisk/score/spec_security/data_attrs/sps_data_attr04.py
cvsvc_apirisk/score/spec_security/data_attrs/sps_data_attr05.py
cvsvc_apirisk/score/spec_security/data_attrs/sps_data_attr06.py
cvsvc_apirisk/score/spec_security/data_attrs/sps_data_attr07.py
cvsvc_apirisk/score/spec_security/data_attrs/sps_data_attr08.py
cvsvc_apirisk/score/spec_security/data_attrs/sps_data_attr09.py
cvsvc_apirisk/score/spec_security/data_attrs/sps_data_attr10.py
impsparc-3.2.2.dist-info/LICENSE.md
impsparc-3.2.2.dist-info/METADATA
impsparc-3.2.2.dist-info/WHEEL
impsparc-3.2.2.dist-info/entry_points.txt
impsparc-3.2.2.dist-info/top_level.txt
impsparc-3.2.2.dist-info/RECORD
