Metadata-Version: 2.1
Name: impsparc
Version: 3.2.2
Summary: API Specification Analysis for Risks and Compliance
Home-page: UNKNOWN
Author: Priyank Chheda
Author-email: priyank.chheda@imperva.com
License: UNKNOWN
Platform: UNKNOWN
Classifier: Programming Language :: Python :: 3
Classifier: Operating System :: OS Independent
Requires-Python: >=3
License-File: LICENSE.md
Requires-Dist: MarkupSafe==2.0.1
Requires-Dist: openapi-spec-validator==0.2.9
Requires-Dist: openapi3==1.0.0
Requires-Dist: prance==0.19.0
Requires-Dist: numpy==1.22.3
Requires-Dist: networkx==2.4
Requires-Dist: parsimonious==0.8.1
Requires-Dist: sanic==20.3.0
Requires-Dist: jinja2==3.0.3
Requires-Dist: idna==2.10
Requires-Dist: PyYAML==5.3
